supertts/__init__.py
supertts/constants.py
supertts/super_tts.py
supertts/utils.py
supertts/providers/__init__.py
supertts/providers/azure_provider.py
supertts/providers/base_provider.py
supertts/providers/google_provider.py
supertts/providers/openai_provider.py
tests/__init__.py
tests/test_azure.py
tests/test_core.py
tests/test_openai.py
supertts-0.0.19.dist-info/LICENSE
supertts-0.0.19.dist-info/METADATA
supertts-0.0.19.dist-info/WHEEL
supertts-0.0.19.dist-info/top_level.txt
supertts-0.0.19.dist-info/RECORD
