Metadata-Version: 2.1
Name: supertts
Version: 0.0.19
Summary: A super TTS package supporting multiple providers.
Author: Aman Kumar
Author-email: 2000.aman.sinha@gmail.com
License-File: LICENSE
Requires-Dist: openai
Provides-Extra: test
Requires-Dist: python-dotenv ; extra == 'test'
